deepxde/__init__.py
deepxde/_version.py
deepxde/callbacks.py
deepxde/config.py
deepxde/display.py
deepxde/losses.py
deepxde/metrics.py
deepxde/model.py
deepxde/real.py
deepxde/backend/__init__.py
deepxde/backend/backend.py
deepxde/backend/set_default_backend.py
deepxde/backend/utils.py
deepxde/backend/jax/__init__.py
deepxde/backend/jax/tensor.py
deepxde/backend/paddle/__init__.py
deepxde/backend/paddle/tensor.py
deepxde/backend/pytorch/__init__.py
deepxde/backend/pytorch/tensor.py
deepxde/backend/tensorflow/__init__.py
deepxde/backend/tensorflow/tensor.py
deepxde/backend/tensorflow_compat_v1/__init__.py
deepxde/backend/tensorflow_compat_v1/tensor.py
deepxde/data/__init__.py
deepxde/data/constraint.py
deepxde/data/data.py
deepxde/data/dataset.py
deepxde/data/fpde.py
deepxde/data/func_constraint.py
deepxde/data/function.py
deepxde/data/function_spaces.py
deepxde/data/helper.py
deepxde/data/ide.py
deepxde/data/mf.py
deepxde/data/pde.py
deepxde/data/pde_operator.py
deepxde/data/quadruple.py
deepxde/data/sampler.py
deepxde/data/triple.py
deepxde/geometry/__init__.py
deepxde/geometry/csg.py
deepxde/geometry/geometry.py
deepxde/geometry/geometry_1d.py
deepxde/geometry/geometry_2d.py
deepxde/geometry/geometry_3d.py
deepxde/geometry/geometry_nd.py
deepxde/geometry/pointcloud.py
deepxde/geometry/sampler.py
deepxde/geometry/timedomain.py
deepxde/gradients/__init__.py
deepxde/gradients/gradients.py
deepxde/gradients/gradients_forward.py
deepxde/gradients/gradients_reverse.py
deepxde/gradients/jacobian.py
deepxde/icbc/__init__.py
deepxde/icbc/boundary_conditions.py
deepxde/icbc/initial_conditions.py
deepxde/nn/__init__.py
deepxde/nn/activations.py
deepxde/nn/deeponet_strategy.py
deepxde/nn/initializers.py
deepxde/nn/regularizers.py
deepxde/nn/jax/__init__.py
deepxde/nn/jax/fnn.py
deepxde/nn/jax/nn.py
deepxde/nn/paddle/__init__.py
deepxde/nn/paddle/deeponet.py
deepxde/nn/paddle/fnn.py
deepxde/nn/paddle/mfnn.py
deepxde/nn/paddle/msffn.py
deepxde/nn/paddle/nn.py
deepxde-1.14.0.dist-info/licenses/LICENSE
deepxde-1.14.0.dist-info/METADATA
deepxde-1.14.0.dist-info/WHEEL
deepxde-1.14.0.dist-info/top_level.txt
deepxde-1.14.0.dist-info/RECORD
