Metadata-Version: 2.4
Name: DeepXDE
Version: 1.14.0
Summary: A library for scientific machine learning
Author-email: Lu Lu <lululxvi@gmail.com>
License: LGPL-2.1
Project-URL: Homepage, https://github.com/lululxvi/deepxde
Project-URL: Bug Tracker, https://github.com/lululxvi/deepxde/issues
Project-URL: Changelog, https://github.com/lululxvi/deepxde/releases
Project-URL: Documentation, https://deepxde.readthedocs.io
Keywords: Deep learning,Differential equations,Machine learning,Neural networks,Physics-informed neural networks,Scientific computing,Scientific machine learning
Classifier: Development Status :: 5 - Production/Stable
Classifier: Intended Audience :: Science/Research
Classifier: License :: OSI Approved :: GNU Lesser General Public License v2 (LGPLv2)
Classifier: Programming Language :: Python :: 3 :: Only
Classifier: Programming Language :: Python :: 3.9
Classifier: Programming Language :: Python :: 3.10
Classifier: Programming Language :: Python :: 3.11
Classifier: Programming Language :: Python :: 3.12
Classifier: Topic :: Scientific/Engineering
Classifier: Topic :: Scientific/Engineering :: Artificial Intelligence
Classifier: Topic :: Scientific/Engineering :: Mathematics
Requires-Python: >=3.9
License-File: LICENSE
Requires-Dist: matplotlib
Requires-Dist: numpy
Requires-Dist: scikit-learn
Requires-Dist: scikit-optimize>=0.9.0
Requires-Dist: scipy
Dynamic: license-file
